odoo/addons/product_code_mandatory/README.rst
odoo/addons/product_code_mandatory/__init__.py
odoo/addons/product_code_mandatory/__manifest__.py
odoo/addons/product_code_mandatory/models/__init__.py
odoo/addons/product_code_mandatory/models/product.py
odoo/addons/product_code_mandatory/static/description/icon.png
odoo/addons/product_code_mandatory/views/product_code_seq.xml
odoo/addons/product_code_mandatory/views/product_view.xml
odoo11_addon_product_code_mandatory-11.0.1.0.0.dist-info/DESCRIPTION.rst
odoo11_addon_product_code_mandatory-11.0.1.0.0.dist-info/METADATA
odoo11_addon_product_code_mandatory-11.0.1.0.0.dist-info/RECORD
odoo11_addon_product_code_mandatory-11.0.1.0.0.dist-info/WHEEL
odoo11_addon_product_code_mandatory-11.0.1.0.0.dist-info/metadata.json
odoo11_addon_product_code_mandatory-11.0.1.0.0.dist-info/top_level.txt
